{
    "paths": [
        {
            "name": "/solutions",
            "lambdaFunction": "solutionFunction",
            "privacy": {
                "protected": true,
                "auth": "rw",
                "unauth": "rw"
            }
        }
    ],
    "resourceName": "solutionApi",
    "apiName": "solutionApi",
    "functionArns": [
        {
            "lambdaFunction": "solutionFunction"
        }
    ],
    "privacy": {
        "auth": 1,
        "unauth": 1,
        "authRoleName": "aiothings-20190217141129-authRole",
        "unAuthRoleName": "aiothings-20190217141129-unauthRole"
    },
    "dependsOn": [
        {
            "category": "function",
            "resourceName": "solutionFunction",
            "attributes": [
                "Name",
                "Arn"
            ]
        }
    ]
}